networksampler/__init__.py
networksampler/sampling.py
networksampler-0.1.0.dist-info/METADATA
networksampler-0.1.0.dist-info/WHEEL
networksampler-0.1.0.dist-info/licenses/LICENSE
networksampler-0.1.0.dist-info/RECORD
