Metadata-Version: 2.1
Name: networksampler
Version: 0.1.0
Summary: Python package to measure network centrality
Author-email: Emiliano del Gobbo <emidelgo@gmail.com>
Classifier: License :: OSI Approved :: GNU Lesser General Public License v3 (LGPLv3)
Classifier: Programming Language :: Python :: 3
Classifier: Programming Language :: Python :: 3.10
Requires-Python: >=3.10
Requires-Dist: networkx>=2.8.0
Requires-Dist: numpy>=1.22
